binprism/__init__.py
binprism/version.py
binprism/core/FourierSeries.py
binprism/core/MomentCalculator.py
binprism/core/PPD.py
binprism/core/Profile.py
binprism/core/__init__.py
binprism/core/io.py
binprism/core/tools/__init__.py
binprism/core/tools/counting.py
binprism/core/tools/plotting.py
binprism/core/tools/sim.py
binprism/util/__init__.py
binprism/util/fit.py
binprism-1.1.1.dist-info/METADATA
binprism-1.1.1.dist-info/WHEEL
binprism-1.1.1.dist-info/license.txt.txt
binprism-1.1.1.dist-info/top_level.txt
binprism-1.1.1.dist-info/RECORD
