Metadata-Version: 2.1
Name: binprism
Version: 1.1.1
Summary: Package for fitting continuous profiles to binned data
Home-page: https://github.com/JoeJimFlood/BinPrism
Author: Joseph J. Flood
Author-email: "Joseph J. Flood" <joejimflood@gmail.com>
License: GNU GPLv3
Keywords: data_analysis,simulation
Classifier: Programming Language :: Python :: 3
Requires-Python: >=3.7
License-File: license.txt.txt
Requires-Dist: numpy
Requires-Dist: pandas
Requires-Dist: scipy
Requires-Dist: matplotlib
